[
  {
    "Preferred Name": "Erik_Knobl",
    "ETH Address": "0x06Ce7AA062c3CfEF67152Ef45147213EE33D42A6",
    "Discord Username": "Erik_Knobl#0082",
    "Discourse username": "Erik_Knobl"
  },
  {
    "Preferred Name": "luan",
    "ETH Address": "0x5952788924bF35B85d2BAA9509349baaF3159cD7",
    "Discord Username": "lu.an#9388",
    "Discourse username": "lu.an#9388"
  },
  {
    "Preferred Name": "ntindle",
    "ETH Address": "0xc535CfdF454110F2D77064443C4310a2C4964b5A",
    "Discord Username": "ntindle#1998",
    "Discourse username": "ntindle"
  },
  {
    "Preferred Name": "Wikist",
    "ETH Address": "0xdf26c161C73D4d02d53aD21863df8623Db38f1ce",
    "Discord Username": "Wikist#4898",
    "Discourse username": "Wikist"
  },
  {
    "Preferred Name": "Narb",
    "ETH Address": "0x9934f8CcFdF5E008aC8c07bf00582A833cd33b99",
    "Discord Username": "Narb | 2669#5172",
    "Discourse username": "Narb"
  },
  {
    "Preferred Name": "Colin",
    "ETH Address": "0x57Dfa643313140B667dF0811d7c70f67aA766038",
    "Discord Username": "Colin4ward#6586",
    "Discourse username": "Colin4ward"
  },
  {
    "Preferred Name": "wolovim",
    "ETH Address": "0x378ff65Cb9E9B83B86AA2534c9991e5B28F1Ec92",
    "Discord Username": "wolovim#8537",
    "Discourse username": "wolovim"
  }
]
